{
  "$schema": "https://ui.shadcn.com/schema/registry-item.json",
  "name": "work-experience-block-01",
  "type": "registry:block",
  "registryDependencies": [
    "work-experience"
  ],
  "files": [
    {
      "path": "src/registry/examples/work-experience-demo.tsx",
      "content": "import type { ExperienceItemType } from \"@/registry/work-experience\";\nimport { WorkExperience } from \"@/registry/work-experience\";\n\nconst WORK_EXPERIENCE: ExperienceItemType[] = [\n  {\n    id: \"kaigan-portfolio\",\n    companyName: \"Personal Projects\",\n    companyLogo: \"/icons/icon-192x192.png\",\n    positions: [\n      {\n        id: \"portfolio-dev\",\n        title: \"Fullstack Student & Portfolio Developer\",\n        employmentPeriod: \"2025 — present\",\n        employmentType: \"Independent\",\n        icon: \"code\",\n        description: `- Built my personal portfolio with Next.js 15, Tailwind v4, and shadcn/ui.\n- Designed and implemented reusable components (theme switcher, typewriter, etc.).\n- Experimented with animations using Motion and Framer Motion.\n- Implemented PWA support and custom registry setup.`,\n        skills: [\n          \"Next.js\",\n          \"React\",\n          \"Tailwind CSS\",\n          \"TypeScript\",\n          \"shadcn/ui\",\n          \"Framer Motion\"\n        ],\n        isExpanded: true,\n      },\n    ],\n    isCurrentEmployer: true,\n  },\n];\n\nexport default function WorkExperienceDemo() {\n  return (\n    <WorkExperience\n      className=\"w-full rounded-lg border\"\n      experiences={WORK_EXPERIENCE}\n    />\n  );\n}\n",
      "type": "registry:component"
    }
  ]
}